mldev_reporting/__init__.py
mldev_reporting/graphic.py
mldev_reporting/loadfile.py
mldev_reporting/report.py
mldev_reporting/report_styles.py
mldev_reporting/supported_file_formats.py
mldev_reporting/table.py
mldev_reporting/assets/cards.min.css
mldev_reporting/assets/core.min.css
mldev_reporting/assets/dark.min.css
mldev_reporting/assets/footer.en.html
mldev_reporting/assets/footer.ru.html
mldev_reporting/assets/header.html
mldev_reporting/assets/light.min.css
mldev_reporting/assets/link.html
mldev_reporting/assets/nav.html
mldev_reporting/assets/res.cards.html
mldev_reporting/assets/res.html
mldev_reporting/assets/styles.min.css
mldev_reporting-0.1.1.dist-info/LICENSE
mldev_reporting-0.1.1.dist-info/METADATA
mldev_reporting-0.1.1.dist-info/WHEEL
mldev_reporting-0.1.1.dist-info/top_level.txt
mldev_reporting-0.1.1.dist-info/RECORD
