Metadata-Version: 2.1
Name: mldev_reporting
Version: 0.1.1
Summary: An extantion library for creatind reports for MLDev
Home-page: https://gitlab.com/mlrep/mldev-reporting
Author: MLRep Team, Alexandra Maratkanova
Author-email: dev@mlrep.org, ola.maratkanova@gmail.com
License: Apache 2.0 license
Classifier: License :: OSI Approved :: Apache Software License
Classifier: Intended Audience :: Developers
Classifier: Intended Audience :: Science/Research
Classifier: Operating System :: POSIX :: Linux
Classifier: Programming Language :: Python :: 3
Classifier: Programming Language :: Python :: 3.7
Classifier: Topic :: Scientific/Engineering :: Artificial Intelligence
License-File: LICENSE
